parrot/__init__.py
parrot/config/__init__.py
parrot/config/config.py
parrot/example_data/dark1.h5
parrot/example_data/dark2.h5
parrot/example_data/light.h5
parrot/load/__init__.py
parrot/load/load.py
parrot/load/recording_device.py
parrot/load/recording_type.py
parrot/plot/WaterAbsorptionLines.csv
parrot/plot/__init__.py
parrot/plot/plot.py
parrot/process/__init__.py
parrot/process/post_process_data.py
parrot/process/prepare_data.py
parrot/process/process_data.py
superparrot-0.1.2.dist-info/METADATA
superparrot-0.1.2.dist-info/WHEEL
superparrot-0.1.2.dist-info/licenses/LICENSE
superparrot-0.1.2.dist-info/RECORD
