Metadata-Version: 2.3
Name: superparrot
Version: 0.1.2
Summary: parrot is able to to process and average continuously recorded THz data.
Project-URL: Source, https://github.com/TimVog/parrot
Project-URL: Documentation, https://timvog.github.io/parrot/
Author-email: Tim Vogel <32876663+TimVog@users.noreply.github.com>
License-Expression: GPL-3.0-or-later
License-File: LICENSE
Keywords: DR,SNR,THz,Terahertz,averaging,dataprocessing,dynamic range,signal-to-noise ratio
Classifier: License :: OSI Approved :: GNU Lesser General Public License v3 or later (LGPLv3+)
Classifier: Operating System :: OS Independent
Classifier: Programming Language :: Python
Classifier: Programming Language :: Python :: 3.8
Classifier: Programming Language :: Python :: 3.9
Classifier: Programming Language :: Python :: 3.10
Classifier: Programming Language :: Python :: 3.11
Classifier: Programming Language :: Python :: 3.12
Requires-Python: >=3.8
Requires-Dist: colorama
Requires-Dist: h5py
Requires-Dist: matplotlib
Requires-Dist: numpy
Requires-Dist: scipy
